<?xml version="1.0" encoding="utf-8" ?>
<updates>
  <update version="1.5">
    <files>
      <file path="Components/LiveSplit.Crash4LoadRemover.dll" status="changed" />
      <file path="Components/LiveSplit.Crash4LoadRemover.pdb" status="changed" />
      <file path="Components/CaptureSampleCore.dll" status="changed" />
      <file path="Components/CaptureSampleCore.pdb" status="changed" />
      <file path="Components/Composition.WindowsRuntimeHelpers.dll" status="changed" />
      <file path="Components/Composition.WindowsRuntimeHelpers.pdb" status="changed" />
      <file path="Components/System.Drawing.Common.dll" status="changed" />
      <file path="Components/SharpDX.Direct3D11.dll" status="changed" />
      <file path="Components/SharpDX.Direct3D11.pdb" status="changed" />
      <file path="Components/SharpDX.Direct3D11.xml" status="changed" />
      <file path="Components/SharpDX.DXGI.dll" status="changed" />
      <file path="Components/SharpDX.DXGI.pdb" status="changed" />
      <file path="Components/SharpDX.DXGI.xml" status="changed" />
      <file path="Components/SharpDX.dll" status="changed" />
      <file path="Components/SharpDX.pdb" status="changed" />
    </files>
    <changelog>
      <change>
        Added "Windows Graphics Capture" support for hardware-accelerated windows. Added fix for PC version having black frames in between load screens.
      </change>
    </changelog>
  </update>
  <update version="1.4">
    <files>
      <file path="Components/LiveSplit.Crash4LoadRemover.dll" status="changed" />
    </files>
    <changelog>
      <change>
        Tweaked the detection parameters a bit to hopefully prevent misdetections when entering levels from the level select menu.
        Added some checks to prevent crashes when invalid values are set for the capture region. 
        Added checkbox for detailed logs. These can be enabled to get more information about the load remover state at every frame in the log files.
        (Only enable that setting if necessary for analysis/debugging, it's costly performance wise.)
      </change>
    </changelog>
  </update>
  <update version="1.3">
    <files>
      <file path="Components/LiveSplit.Crash4LoadRemover.dll" status="changed" />
    </files>
    <changelog>
      <change>
        Reworked the detection to use gradients as well. This should work for all languages ideally, but needs testing.
      </change>
    </changelog>
  </update>
  <update version="1.2">
    <files>
      <file path="Components/LiveSplit.Crash4LoadRemover.dll" status="changed" />
    </files>
    <changelog>
      <change>
        Made the detection of the blue/black swirl more lenient.
      </change>
    </changelog>
  </update>
  <update version="1.1">
    <files>
      <file path="Components/LiveSplit.Crash4LoadRemover.dll" status="changed" />
    </files>
    <changelog>
      <change>
        Initial version of the "Crash Bandicoot 4: It's About Time" load remover for the full game. 
        Should ideally work out-of-the box if you choose your capture region and scaling correctly.
      </change>
    </changelog>
  </update>
</updates>
